fu_downloader/__init__.py
fu_downloader/cli.py
fu_downloader-0.1.0.dist-info/METADATA
fu_downloader-0.1.0.dist-info/WHEEL
fu_downloader-0.1.0.dist-info/entry_points.txt
fu_downloader-0.1.0.dist-info/top_level.txt
fu_downloader-0.1.0.dist-info/RECORD
