Metadata-Version: 2.4
Name: fu_downloader
Version: 0.1.0
Summary: CLI tool để tải ảnh từ thread FuOverflow
Author: Kappy
Author-email: Kappy <your_email@example.com>
License: MIT
Requires-Python: >=3.7
Requires-Dist: requests
Requires-Dist: beautifulsoup4
Requires-Dist: click
Dynamic: author
Dynamic: requires-python
